{
  "fetched_at": 1758140729,
  "placeId": 109983668079237,
  "servers": [
    {
      "id": "5e07263f-40ad-45f2-9a93-4b004b9a7764",
      "playing": 7,
      "maxPlayers": 8,
      "created": null
    },
    {
      "id": "9440eca3-4e50-4954-893e-3851013a8ef3",
      "playing": 7,
      "maxPlayers": 8,
      "created": null
    },
    {
      "id": "8e13b700-91b9-45fa-84d7-b8c8c2273665",
      "playing": 7,
      "maxPlayers": 8,
      "created": null
    },
    {
      "id": "457c8b07-8d42-489d-ab6f-6eed68567d8e",
      "playing": 7,
      "maxPlayers": 8,
      "created": null
    },
    {
      "id": "39ce00b9-f879-46e8-b181-06a2999ab72c",
      "playing": 7,
      "maxPlayers": 8,
      "created": null
    },
    {
      "id": "67ddf649-8e4e-4e59-8b54-124864c26f1b",
      "playing": 7,
      "maxPlayers": 8,
      "created": null
    },
    {
      "id": "86d05ded-fd55-4a29-a6da-6ea3c625039f",
      "playing": 7,
      "maxPlayers": 8,
      "created": null
    },
    {
      "id": "f742ed35-f9a4-42db-b015-86617f1db457",
      "playing": 7,
      "maxPlayers": 8,
      "created": null
    },
    {
      "id": "27ae8500-1a47-42fe-9aaf-9390f7196b41",
      "playing": 7,
      "maxPlayers": 8,
      "created": null
    },
    {
      "id": "c41b20c8-2879-4272-9cdd-08fc786fa0ba",
      "playing": 7,
      "maxPlayers": 8,
      "created": null
    },
    {
      "id": "0e1ce050-1bec-4de5-96ae-bbbdaee87b05",
      "playing": 7,
      "maxPlayers": 8,
      "created": null
    },
    {
      "id": "8de1cce9-43a2-4db5-b0f8-c7fc9e5ec557",
      "playing": 7,
      "maxPlayers": 8,
      "created": null
    },
    {
      "id": "0dc3622b-2724-46be-a223-0bccc4bd3c68",
      "playing": 7,
      "maxPlayers": 8,
      "created": null
    },
    {
      "id": "ee05e92f-1e26-4ed9-b5e1-86b2e6ee10c4",
      "playing": 7,
      "maxPlayers": 8,
      "created": null
    },
    {
      "id": "8f96429e-7893-4322-b888-344c44abd6d4",
      "playing": 7,
      "maxPlayers": 8,
      "created": null
    },
    {
      "id": "c18d96db-9cc7-4f43-ad2a-7c395ffbef55",
      "playing": 7,
      "maxPlayers": 8,
      "created": null
    },
    {
      "id": "d1bcfa0e-1354-44e3-9566-704127af381d",
      "playing": 7,
      "maxPlayers": 8,
      "created": null
    },
    {
      "id": "55c046f5-3264-4e81-99a2-d2ccf3bf704b",
      "playing": 7,
      "maxPlayers": 8,
      "created": null
    },
    {
      "id": "3a4e72af-1402-42a6-871c-84c50f2f3c16",
      "playing": 7,
      "maxPlayers": 8,
      "created": null
    },
    {
      "id": "3d9c92b5-0eaf-47c7-ab48-32ddf0ea57be",
      "playing": 7,
      "maxPlayers": 8,
      "created": null
    },
    {
      "id": "b27b08a9-a5d1-4338-ac18-225aa9c27b88",
      "playing": 7,
      "maxPlayers": 8,
      "created": null
    },
    {
      "id": "667a2599-d470-4209-8fc8-806041dd551c",
      "playing": 7,
      "maxPlayers": 8,
      "created": null
    },
    {
      "id": "c4f668a7-f517-470b-946a-8f4c6a43efe5",
      "playing": 7,
      "maxPlayers": 8,
      "created": null
    },
    {
      "id": "63b696a9-be10-4c46-99a2-4188c83a0f44",
      "playing": 7,
      "maxPlayers": 8,
      "created": null
    },
    {
      "id": "64809e3f-a9a7-484e-b47e-ff7b5d1f572a",
      "playing": 7,
      "maxPlayers": 8,
      "created": null
    },
    {
      "id": "b87398ab-65bc-4694-81ad-3dd899b5a5c6",
      "playing": 7,
      "maxPlayers": 8,
      "created": null
    },
    {
      "id": "69cafdc8-34d2-4aab-8e3a-935554162e61",
      "playing": 7,
      "maxPlayers": 8,
      "created": null
    },
    {
      "id": "bad173af-5fb7-429d-944c-549c3e407656",
      "playing": 7,
      "maxPlayers": 8,
      "created": null
    },
    {
      "id": "876016bb-265e-4d4a-9f80-4d4311ded75f",
      "playing": 7,
      "maxPlayers": 8,
      "created": null
    },
    {
      "id": "e1d08fc9-3b24-408f-9929-adf998050792",
      "playing": 7,
      "maxPlayers": 8,
      "created": null
    },
    {
      "id": "62227fe3-bbd0-45f1-b22d-edf86e3bcceb",
      "playing": 7,
      "maxPlayers": 8,
      "created": null
    },
    {
      "id": "860f5783-5a37-47f4-a2ae-92038bb62907",
      "playing": 7,
      "maxPlayers": 8,
      "created": null
    },
    {
      "id": "e24b0c8b-c120-49b1-b8e7-ffff50304840",
      "playing": 7,
      "maxPlayers": 8,
      "created": null
    },
    {
      "id": "05f10cc5-5d8a-4c7e-9de0-0389be25f488",
      "playing": 7,
      "maxPlayers": 8,
      "created": null
    },
    {
      "id": "86bfbec2-813d-4e5a-89eb-61d67efe2cac",
      "playing": 7,
      "maxPlayers": 8,
      "created": null
    },
    {
      "id": "c1e675a9-fad4-411b-980e-aeb681cf10a3",
      "playing": 7,
      "maxPlayers": 8,
      "created": null
    },
    {
      "id": "6ec5c143-c024-4e5b-8d90-c894002a1771",
      "playing": 7,
      "maxPlayers": 8,
      "created": null
    },
    {
      "id": "526b8af9-63e9-4f73-aeb2-e8b4c66ffff5",
      "playing": 7,
      "maxPlayers": 8,
      "created": null
    },
    {
      "id": "3660448d-3dc2-42d3-a335-5188f28831bf",
      "playing": 7,
      "maxPlayers": 8,
      "created": null
    },
    {
      "id": "1b89914a-ba33-4ae4-b7a4-150e33bfe7c0",
      "playing": 7,
      "maxPlayers": 8,
      "created": null
    },
    {
      "id": "8acbde90-7616-47d4-a235-e624a8f1fc78",
      "playing": 7,
      "maxPlayers": 8,
      "created": null
    },
    {
      "id": "1f71796f-2b75-4341-9ea2-1c974db67943",
      "playing": 7,
      "maxPlayers": 8,
      "created": null
    },
    {
      "id": "4adf0aa7-4f87-46dc-b348-cfc02049e2c3",
      "playing": 7,
      "maxPlayers": 8,
      "created": null
    },
    {
      "id": "620f86a2-83ed-4456-becb-c8d1f1461271",
      "playing": 7,
      "maxPlayers": 8,
      "created": null
    },
    {
      "id": "9f6ead19-0026-47e7-838c-10d4424fa2c5",
      "playing": 7,
      "maxPlayers": 8,
      "created": null
    },
    {
      "id": "326ab106-aec0-422c-971d-8563355a5d82",
      "playing": 7,
      "maxPlayers": 8,
      "created": null
    },
    {
      "id": "604a5e7c-8e78-4e83-95cc-d13db973735f",
      "playing": 7,
      "maxPlayers": 8,
      "created": null
    },
    {
      "id": "7048a583-10ef-4ff6-88a9-043fb04c7821",
      "playing": 7,
      "maxPlayers": 8,
      "created": null
    },
    {
      "id": "7900e56e-1da4-4e53-9f45-1f02020b6ca0",
      "playing": 7,
      "maxPlayers": 8,
      "created": null
    },
    {
      "id": "c32962f4-0dfa-44ea-b620-d956941e18d6",
      "playing": 7,
      "maxPlayers": 8,
      "created": null
    },
    {
      "id": "3b95bf77-a655-4e2f-a48f-749b73b9d831",
      "playing": 7,
      "maxPlayers": 8,
      "created": null
    },
    {
      "id": "235132e2-da66-4b2e-9ec1-74f51e83b4ea",
      "playing": 7,
      "maxPlayers": 8,
      "created": null
    },
    {
      "id": "af91d60e-cbc8-4e40-9322-bdf2af8b6db6",
      "playing": 7,
      "maxPlayers": 8,
      "created": null
    },
    {
      "id": "8fe3bc1d-7fb0-49e3-afc1-84be9ec78857",
      "playing": 7,
      "maxPlayers": 8,
      "created": null
    },
    {
      "id": "3e9158d4-8026-4b23-af4c-ffa63ffb043b",
      "playing": 7,
      "maxPlayers": 8,
      "created": null
    },
    {
      "id": "5c4ad87a-03fb-4b51-a7bf-a7e3a0992e0f",
      "playing": 7,
      "maxPlayers": 8,
      "created": null
    },
    {
      "id": "b7943bcf-2737-4dee-bffc-a25e18298af7",
      "playing": 7,
      "maxPlayers": 8,
      "created": null
    },
    {
      "id": "1bd8d859-1f77-44bf-b83c-862ea7511cc5",
      "playing": 7,
      "maxPlayers": 8,
      "created": null
    },
    {
      "id": "1b62f021-d2bc-43c1-b971-7162888cdbea",
      "playing": 7,
      "maxPlayers": 8,
      "created": null
    },
    {
      "id": "43fff4ab-a8f4-42a1-87b4-48567a6d77e5",
      "playing": 7,
      "maxPlayers": 8,
      "created": null
    },
    {
      "id": "9859e1d6-a990-41ac-b58d-d6a6b091bc91",
      "playing": 7,
      "maxPlayers": 8,
      "created": null
    },
    {
      "id": "eeaf5cc0-9ca9-4752-8327-189e63a13c1b",
      "playing": 7,
      "maxPlayers": 8,
      "created": null
    },
    {
      "id": "f777e835-b61b-4e98-bef3-7b030a5e4f49",
      "playing": 7,
      "maxPlayers": 8,
      "created": null
    },
    {
      "id": "2b68a9be-7d1f-42f8-9db6-862ad4fa7feb",
      "playing": 7,
      "maxPlayers": 8,
      "created": null
    },
    {
      "id": "77f1427a-4a39-48d5-be3f-a66b388a176f",
      "playing": 7,
      "maxPlayers": 8,
      "created": null
    },
    {
      "id": "fc09d02b-5955-489d-a2fa-f6822533e12d",
      "playing": 7,
      "maxPlayers": 8,
      "created": null
    },
    {
      "id": "8f0c6709-5195-43c3-aeb3-2b97f55f38a1",
      "playing": 7,
      "maxPlayers": 8,
      "created": null
    },
    {
      "id": "1cf6dd2a-2237-4881-8fb8-6d399fe6c9cd",
      "playing": 7,
      "maxPlayers": 8,
      "created": null
    },
    {
      "id": "3381c8c0-d968-4bea-9b72-be62b0586c5c",
      "playing": 7,
      "maxPlayers": 8,
      "created": null
    },
    {
      "id": "f60240b8-dc43-45f9-864e-88d32900e319",
      "playing": 7,
      "maxPlayers": 8,
      "created": null
    },
    {
      "id": "77618669-32a0-49cc-9e3d-1262ef9dd6cd",
      "playing": 7,
      "maxPlayers": 8,
      "created": null
    },
    {
      "id": "a5c0df57-edc1-4aa7-920c-5d7bbbac14b5",
      "playing": 7,
      "maxPlayers": 8,
      "created": null
    },
    {
      "id": "5ef6f615-1e86-45d0-a664-95af15efae3c",
      "playing": 7,
      "maxPlayers": 8,
      "created": null
    },
    {
      "id": "ad03ee83-5aee-4b51-b04c-40383fc67756",
      "playing": 7,
      "maxPlayers": 8,
      "created": null
    },
    {
      "id": "1afc57d3-77f1-42c7-a825-ed7630f1dd42",
      "playing": 7,
      "maxPlayers": 8,
      "created": null
    },
    {
      "id": "ad8e83f9-1d08-47af-a062-3f1b2f506f4b",
      "playing": 7,
      "maxPlayers": 8,
      "created": null
    },
    {
      "id": "110633bb-1fc3-46e7-b730-6a7b47387769",
      "playing": 7,
      "maxPlayers": 8,
      "created": null
    },
    {
      "id": "30dd5d67-cb9a-46eb-8dec-fdaca2e92b66",
      "playing": 7,
      "maxPlayers": 8,
      "created": null
    },
    {
      "id": "5c322c94-ae1c-44e8-b085-3114d6fc54da",
      "playing": 7,
      "maxPlayers": 8,
      "created": null
    },
    {
      "id": "4e608023-90ca-44d1-a2f7-252bb650b502",
      "playing": 7,
      "maxPlayers": 8,
      "created": null
    },
    {
      "id": "0c02517a-f667-44fd-b02b-f9bdfc3daf3e",
      "playing": 7,
      "maxPlayers": 8,
      "created": null
    },
    {
      "id": "1bfaa89d-873a-4577-be49-bf26bb9f52d9",
      "playing": 7,
      "maxPlayers": 8,
      "created": null
    },
    {
      "id": "8ca2eca2-058d-4cad-8e85-bb2364c5fc30",
      "playing": 7,
      "maxPlayers": 8,
      "created": null
    },
    {
      "id": "4daef1be-4558-40f5-8b41-a1cb4951a596",
      "playing": 7,
      "maxPlayers": 8,
      "created": null
    },
    {
      "id": "27fa6ea6-6131-4aeb-bab1-83e2e3511574",
      "playing": 7,
      "maxPlayers": 8,
      "created": null
    },
    {
      "id": "d33eb2d7-caec-4123-aaa0-03146679bbdd",
      "playing": 7,
      "maxPlayers": 8,
      "created": null
    },
    {
      "id": "2719d318-27a8-4412-bba9-3f58d55c1950",
      "playing": 7,
      "maxPlayers": 8,
      "created": null
    },
    {
      "id": "edeef3f4-060f-487b-a2a8-63f84e6f9094",
      "playing": 7,
      "maxPlayers": 8,
      "created": null
    },
    {
      "id": "40de35a8-aeba-4e86-ba02-83ad3fffb8e7",
      "playing": 7,
      "maxPlayers": 8,
      "created": null
    },
    {
      "id": "347f5cbb-671f-4d53-a9b0-d868608466d8",
      "playing": 7,
      "maxPlayers": 8,
      "created": null
    },
    {
      "id": "441b6bfc-762c-4355-b4ae-efcc527f85b8",
      "playing": 7,
      "maxPlayers": 8,
      "created": null
    },
    {
      "id": "a37c898f-d31a-46f5-af38-aec922627a4c",
      "playing": 7,
      "maxPlayers": 8,
      "created": null
    },
    {
      "id": "c089f13a-068b-4545-b4d7-1125109f25cc",
      "playing": 7,
      "maxPlayers": 8,
      "created": null
    },
    {
      "id": "c744d616-e5ff-4326-84fc-27d827d835f2",
      "playing": 7,
      "maxPlayers": 8,
      "created": null
    },
    {
      "id": "c084fc24-2c20-426a-a72b-fd0c6fea3f44",
      "playing": 7,
      "maxPlayers": 8,
      "created": null
    },
    {
      "id": "42e7650b-dbd1-4df4-8d99-f9191886fd6d",
      "playing": 7,
      "maxPlayers": 8,
      "created": null
    },
    {
      "id": "ddc7a6b9-3e64-44b0-8e28-ba1c5d6e36c3",
      "playing": 7,
      "maxPlayers": 8,
      "created": null
    },
    {
      "id": "4f36eca6-22c2-4b3d-a733-c77ff0296d0f",
      "playing": 7,
      "maxPlayers": 8,
      "created": null
    },
    {
      "id": "2a120351-88fd-468e-bb71-1063511986ea",
      "playing": 7,
      "maxPlayers": 8,
      "created": null
    },
    {
      "id": "4515ebe6-19b3-46ed-b641-b20c159ab88b",
      "playing": 7,
      "maxPlayers": 8,
      "created": null
    },
    {
      "id": "e0cb563e-77c6-453e-a5fd-3aaa93daf6b1",
      "playing": 7,
      "maxPlayers": 8,
      "created": null
    },
    {
      "id": "71589c90-0035-46b1-9b78-fbbdde70e03c",
      "playing": 7,
      "maxPlayers": 8,
      "created": null
    },
    {
      "id": "5a7e8bff-6957-429c-883b-5ae03c089b4c",
      "playing": 7,
      "maxPlayers": 8,
      "created": null
    },
    {
      "id": "8d14d7b5-ad39-47cd-a12f-8e529f2aee16",
      "playing": 7,
      "maxPlayers": 8,
      "created": null
    },
    {
      "id": "20cc60ac-1be6-49ba-9da1-91c4115e4475",
      "playing": 7,
      "maxPlayers": 8,
      "created": null
    },
    {
      "id": "a5778052-b4fb-4e45-8fd4-660c03871ffb",
      "playing": 7,
      "maxPlayers": 8,
      "created": null
    },
    {
      "id": "7888672e-e1e2-478b-bbc0-25d4f72d06f9",
      "playing": 7,
      "maxPlayers": 8,
      "created": null
    },
    {
      "id": "a8f98737-e426-4751-bdc5-697dbd63c17d",
      "playing": 7,
      "maxPlayers": 8,
      "created": null
    },
    {
      "id": "6ef825b6-4c36-408b-bcbb-e9be19674f12",
      "playing": 7,
      "maxPlayers": 8,
      "created": null
    },
    {
      "id": "01a88420-af51-4f42-af43-7d74aaeff4dc",
      "playing": 7,
      "maxPlayers": 8,
      "created": null
    },
    {
      "id": "474e607e-a92b-4feb-a42c-287e4c7c9ea9",
      "playing": 7,
      "maxPlayers": 8,
      "created": null
    },
    {
      "id": "9bda89b2-2815-4ecf-b16a-a34f7dabc380",
      "playing": 7,
      "maxPlayers": 8,
      "created": null
    },
    {
      "id": "216a64c8-a186-4cfb-af8f-d27e9f76a748",
      "playing": 7,
      "maxPlayers": 8,
      "created": null
    },
    {
      "id": "3c3d94af-4a34-4946-9060-daea86180cd1",
      "playing": 7,
      "maxPlayers": 8,
      "created": null
    },
    {
      "id": "53b9b579-48c9-4f73-8394-e647491ed101",
      "playing": 7,
      "maxPlayers": 8,
      "created": null
    },
    {
      "id": "6b3c6f29-216e-44ca-b80f-ad49adaac7d2",
      "playing": 7,
      "maxPlayers": 8,
      "created": null
    },
    {
      "id": "0507cf65-e5d7-4979-bf65-b31fe2fef6c7",
      "playing": 7,
      "maxPlayers": 8,
      "created": null
    },
    {
      "id": "03974f43-52f5-419e-a739-c8cba0d1839d",
      "playing": 7,
      "maxPlayers": 8,
      "created": null
    },
    {
      "id": "b44a054c-0efd-4568-af0d-95b5776fbda5",
      "playing": 7,
      "maxPlayers": 8,
      "created": null
    },
    {
      "id": "ea3110e6-56ea-43d9-a168-7529c87f3c6b",
      "playing": 7,
      "maxPlayers": 8,
      "created": null
    },
    {
      "id": "2f52a3f3-7ace-44fa-a65f-4864be87b5ca",
      "playing": 7,
      "maxPlayers": 8,
      "created": null
    },
    {
      "id": "9bda4a6e-c29a-4161-b0f4-e5c82c57c033",
      "playing": 7,
      "maxPlayers": 8,
      "created": null
    },
    {
      "id": "c62e6610-7e34-466d-9590-04a91cb74c8b",
      "playing": 7,
      "maxPlayers": 8,
      "created": null
    },
    {
      "id": "4b0528e2-9cb8-49ac-894b-3e30bf6031cf",
      "playing": 7,
      "maxPlayers": 8,
      "created": null
    },
    {
      "id": "2bffc01a-984a-44de-a617-7a4d3b7c7e17",
      "playing": 7,
      "maxPlayers": 8,
      "created": null
    },
    {
      "id": "41ca1ed3-349d-4fcf-8ef1-59e8b08f0307",
      "playing": 7,
      "maxPlayers": 8,
      "created": null
    },
    {
      "id": "19f56ce2-8efe-40d8-9b6f-46bd2db09a87",
      "playing": 7,
      "maxPlayers": 8,
      "created": null
    },
    {
      "id": "5fefb1f1-ab46-42c9-aa80-5a6d20ddf900",
      "playing": 7,
      "maxPlayers": 8,
      "created": null
    },
    {
      "id": "78897632-43ac-4106-b69c-6cee36f8df7f",
      "playing": 7,
      "maxPlayers": 8,
      "created": null
    },
    {
      "id": "87e17ccd-e6fa-4993-ad5f-46e23755d97a",
      "playing": 7,
      "maxPlayers": 8,
      "created": null
    },
    {
      "id": "4d2a8a5e-df31-4afb-a41f-d731ffe086a8",
      "playing": 7,
      "maxPlayers": 8,
      "created": null
    },
    {
      "id": "07a12f1b-b72c-456d-8a0b-b712eb4e381e",
      "playing": 7,
      "maxPlayers": 8,
      "created": null
    },
    {
      "id": "3898759d-42ee-4cf3-b453-949158bbab3e",
      "playing": 7,
      "maxPlayers": 8,
      "created": null
    },
    {
      "id": "c805cd9d-dc4b-4b5e-a550-600bc432cf21",
      "playing": 7,
      "maxPlayers": 8,
      "created": null
    },
    {
      "id": "94c25e56-5ff9-43f8-be95-2c907cf25f1c",
      "playing": 7,
      "maxPlayers": 8,
      "created": null
    },
    {
      "id": "0ff036ce-34a8-42cb-8d96-a00e53091304",
      "playing": 7,
      "maxPlayers": 8,
      "created": null
    },
    {
      "id": "373f5a3a-1c9d-414d-852c-55b45acffef4",
      "playing": 7,
      "maxPlayers": 8,
      "created": null
    },
    {
      "id": "9e0340a9-32d3-4119-ae9c-5000ca1d9384",
      "playing": 7,
      "maxPlayers": 8,
      "created": null
    },
    {
      "id": "737d8297-5fec-4add-ba93-1854af4df7e0",
      "playing": 7,
      "maxPlayers": 8,
      "created": null
    },
    {
      "id": "2ab74748-5a6f-4e77-a033-ef8992f4543d",
      "playing": 7,
      "maxPlayers": 8,
      "created": null
    },
    {
      "id": "77158094-95fc-4ad5-98c1-da7eb612b386",
      "playing": 7,
      "maxPlayers": 8,
      "created": null
    },
    {
      "id": "53f17db9-c605-4fb0-8d94-91658f6f8dde",
      "playing": 7,
      "maxPlayers": 8,
      "created": null
    },
    {
      "id": "f1a1c68c-3146-4577-99c0-d9ca77893c43",
      "playing": 7,
      "maxPlayers": 8,
      "created": null
    },
    {
      "id": "8df770f5-a805-41b9-9b3c-b968066d7d2d",
      "playing": 7,
      "maxPlayers": 8,
      "created": null
    },
    {
      "id": "45bb44a8-aa37-41ae-9c51-180f69c625cd",
      "playing": 7,
      "maxPlayers": 8,
      "created": null
    },
    {
      "id": "50b6b1af-0f95-4e90-a387-95b44e7b8b6e",
      "playing": 7,
      "maxPlayers": 8,
      "created": null
    },
    {
      "id": "453a4019-6adb-42ae-87ec-6596ddfa0df6",
      "playing": 7,
      "maxPlayers": 8,
      "created": null
    },
    {
      "id": "e077321c-3148-4b0a-8fef-38c096f406f5",
      "playing": 7,
      "maxPlayers": 8,
      "created": null
    },
    {
      "id": "5c951838-5d38-4870-8af9-9ea04357255b",
      "playing": 7,
      "maxPlayers": 8,
      "created": null
    },
    {
      "id": "66295576-a273-4a3e-91c2-f16e9a09148c",
      "playing": 7,
      "maxPlayers": 8,
      "created": null
    },
    {
      "id": "658912cb-88ed-425c-b3ca-a9f9d0dadfc9",
      "playing": 7,
      "maxPlayers": 8,
      "created": null
    },
    {
      "id": "246bdb73-e9a8-4635-af57-c763c9fa7311",
      "playing": 7,
      "maxPlayers": 8,
      "created": null
    },
    {
      "id": "1f067a02-b86b-4a12-b6f8-6128ada501da",
      "playing": 7,
      "maxPlayers": 8,
      "created": null
    },
    {
      "id": "6aad8978-552c-4652-a9bd-6660a82d3c03",
      "playing": 7,
      "maxPlayers": 8,
      "created": null
    },
    {
      "id": "9e7ec2ab-416d-4a0d-827a-54a1cf89bc9d",
      "playing": 7,
      "maxPlayers": 8,
      "created": null
    },
    {
      "id": "c8d9c3e7-0605-4f6e-850e-0fd1fe55ac32",
      "playing": 7,
      "maxPlayers": 8,
      "created": null
    },
    {
      "id": "10848fd2-46ea-4587-a0c5-57eb09ac5c90",
      "playing": 7,
      "maxPlayers": 8,
      "created": null
    },
    {
      "id": "633841eb-3979-47cf-9685-26374eef5dcc",
      "playing": 7,
      "maxPlayers": 8,
      "created": null
    },
    {
      "id": "a81d6e29-0346-46d1-845f-d58d89f3a07c",
      "playing": 7,
      "maxPlayers": 8,
      "created": null
    },
    {
      "id": "8a761691-6560-4d18-b7a1-4f0eee097cda",
      "playing": 7,
      "maxPlayers": 8,
      "created": null
    },
    {
      "id": "57d50741-ca79-4439-a03e-1a9f159d1ba1",
      "playing": 7,
      "maxPlayers": 8,
      "created": null
    },
    {
      "id": "0004454c-5f68-401f-a0f8-81978144578c",
      "playing": 7,
      "maxPlayers": 8,
      "created": null
    },
    {
      "id": "748b7f50-c3b1-4440-b52a-7899d6bee837",
      "playing": 7,
      "maxPlayers": 8,
      "created": null
    },
    {
      "id": "42a12ff9-0890-4136-8de8-8f4dde8f3e01",
      "playing": 7,
      "maxPlayers": 8,
      "created": null
    },
    {
      "id": "2929635c-aaa8-48a1-977c-5e948abc57c3",
      "playing": 7,
      "maxPlayers": 8,
      "created": null
    },
    {
      "id": "a56e43db-84f4-4786-b555-0bda13ad46e0",
      "playing": 7,
      "maxPlayers": 8,
      "created": null
    },
    {
      "id": "f290dca9-6449-47c9-ba65-8db1e0cea229",
      "playing": 7,
      "maxPlayers": 8,
      "created": null
    },
    {
      "id": "646220cf-f837-4f01-82fa-804f57d1c5b5",
      "playing": 7,
      "maxPlayers": 8,
      "created": null
    },
    {
      "id": "7c620017-acd4-4648-967d-872b5c3f780c",
      "playing": 7,
      "maxPlayers": 8,
      "created": null
    },
    {
      "id": "fd5ca27c-8acf-473d-a3cf-cacc78252001",
      "playing": 7,
      "maxPlayers": 8,
      "created": null
    },
    {
      "id": "5b38e024-b19c-4b67-b390-e67c81005b6f",
      "playing": 7,
      "maxPlayers": 8,
      "created": null
    },
    {
      "id": "b82d1da1-6853-4ee7-9bca-6458c590ea3a",
      "playing": 7,
      "maxPlayers": 8,
      "created": null
    },
    {
      "id": "a6c66fcf-2903-4645-8fe1-602c86d2049f",
      "playing": 7,
      "maxPlayers": 8,
      "created": null
    },
    {
      "id": "be1d8368-8400-44e4-948b-f2f23e118548",
      "playing": 7,
      "maxPlayers": 8,
      "created": null
    },
    {
      "id": "f6aaf486-fb98-416b-8c84-e96230e5a4ef",
      "playing": 7,
      "maxPlayers": 8,
      "created": null
    },
    {
      "id": "73a60a1f-6018-4f6b-80f1-bdf39bb91a14",
      "playing": 7,
      "maxPlayers": 8,
      "created": null
    },
    {
      "id": "0ca57b77-d757-4d24-9a9a-90eec98f03a3",
      "playing": 7,
      "maxPlayers": 8,
      "created": null
    },
    {
      "id": "d437280c-8018-4204-be57-9d0c68677abd",
      "playing": 7,
      "maxPlayers": 8,
      "created": null
    },
    {
      "id": "bfa17a30-8766-4953-8dd0-30de080158b2",
      "playing": 7,
      "maxPlayers": 8,
      "created": null
    },
    {
      "id": "73d23030-28bc-4fb4-a231-a13abe7dcd41",
      "playing": 7,
      "maxPlayers": 8,
      "created": null
    },
    {
      "id": "3b013766-4aad-4191-9a3f-a75ea604f1ae",
      "playing": 7,
      "maxPlayers": 8,
      "created": null
    },
    {
      "id": "989c0638-b429-4b03-8da2-1a372ba9f807",
      "playing": 7,
      "maxPlayers": 8,
      "created": null
    },
    {
      "id": "b36e7c43-2d3c-4b85-af98-a7a2fe10b76b",
      "playing": 7,
      "maxPlayers": 8,
      "created": null
    },
    {
      "id": "123f494f-1b4e-49ae-aea9-d9003c666322",
      "playing": 7,
      "maxPlayers": 8,
      "created": null
    },
    {
      "id": "b816e5c5-7b0b-401a-abcb-1ed47c97c50e",
      "playing": 7,
      "maxPlayers": 8,
      "created": null
    },
    {
      "id": "0248cbae-860f-4411-a2a8-c7a6c0efec94",
      "playing": 7,
      "maxPlayers": 8,
      "created": null
    },
    {
      "id": "f0b770f5-b8eb-4267-a0b0-4447c21c64e5",
      "playing": 7,
      "maxPlayers": 8,
      "created": null
    },
    {
      "id": "153b9a70-62d9-4cef-8e70-cb36beb78034",
      "playing": 7,
      "maxPlayers": 8,
      "created": null
    },
    {
      "id": "39c3258d-1d57-4301-a957-c016853b8af2",
      "playing": 7,
      "maxPlayers": 8,
      "created": null
    },
    {
      "id": "1780f98b-0382-40f1-b348-84ef9792ab55",
      "playing": 7,
      "maxPlayers": 8,
      "created": null
    },
    {
      "id": "335a4c35-ddde-4461-8a87-45d2410f4ef0",
      "playing": 7,
      "maxPlayers": 8,
      "created": null
    },
    {
      "id": "bf56c0a2-01c9-4253-a42c-cf7ab82a7a65",
      "playing": 7,
      "maxPlayers": 8,
      "created": null
    },
    {
      "id": "12bc8c37-6c1c-4731-a728-1b906d007afa",
      "playing": 7,
      "maxPlayers": 8,
      "created": null
    },
    {
      "id": "996500cf-eeae-480c-b2fc-712b76d0f5ab",
      "playing": 7,
      "maxPlayers": 8,
      "created": null
    },
    {
      "id": "410396f1-c726-49e4-bde1-131d4b4af424",
      "playing": 7,
      "maxPlayers": 8,
      "created": null
    },
    {
      "id": "c5d817b4-d028-4f04-93e6-4defff5fe418",
      "playing": 7,
      "maxPlayers": 8,
      "created": null
    },
    {
      "id": "aefd1619-2f5e-4386-8c0f-3e95a96d7795",
      "playing": 7,
      "maxPlayers": 8,
      "created": null
    },
    {
      "id": "cb41cc44-3f7d-453f-b13c-e873843989fb",
      "playing": 7,
      "maxPlayers": 8,
      "created": null
    },
    {
      "id": "7134476f-3489-4bf0-8e42-c928ed47d5c8",
      "playing": 7,
      "maxPlayers": 8,
      "created": null
    },
    {
      "id": "8fa50e49-3e71-4c92-ab1f-e6fe60df05ce",
      "playing": 7,
      "maxPlayers": 8,
      "created": null
    },
    {
      "id": "e3acfc12-e4b6-4fc6-94b2-801ca9b9cdf0",
      "playing": 7,
      "maxPlayers": 8,
      "created": null
    },
    {
      "id": "92dd1e28-2dba-4c15-a97d-d9ee3eb099e8",
      "playing": 7,
      "maxPlayers": 8,
      "created": null
    },
    {
      "id": "1832fde4-f6cf-414b-8dca-300a3a94dd42",
      "playing": 7,
      "maxPlayers": 8,
      "created": null
    },
    {
      "id": "2ed0d0cf-04d1-4724-affc-2a1a80dddeab",
      "playing": 7,
      "maxPlayers": 8,
      "created": null
    },
    {
      "id": "d9d841c3-e6df-4a9f-a4b7-01d5cc352e38",
      "playing": 7,
      "maxPlayers": 8,
      "created": null
    },
    {
      "id": "21bb87f5-093b-401e-a418-5466ec6f8c71",
      "playing": 7,
      "maxPlayers": 8,
      "created": null
    },
    {
      "id": "22f80f73-cd9b-4b1d-940e-aec131f9155c",
      "playing": 7,
      "maxPlayers": 8,
      "created": null
    },
    {
      "id": "5b58407f-b99c-4f92-b69c-f176f34abb12",
      "playing": 7,
      "maxPlayers": 8,
      "created": null
    },
    {
      "id": "e4add22b-6c07-47e3-8b67-f4143ff9c9ed",
      "playing": 7,
      "maxPlayers": 8,
      "created": null
    },
    {
      "id": "a4eba2e2-ba16-40ad-9ca3-0f36fb43f649",
      "playing": 7,
      "maxPlayers": 8,
      "created": null
    },
    {
      "id": "fb114578-e0ee-4875-b5ac-a4298a094481",
      "playing": 7,
      "maxPlayers": 8,
      "created": null
    },
    {
      "id": "37bf3ab5-5fd3-4cef-9cc5-b2202e53a557",
      "playing": 7,
      "maxPlayers": 8,
      "created": null
    },
    {
      "id": "7f621038-b71e-4fb6-a2df-7d3e834b8c0c",
      "playing": 7,
      "maxPlayers": 8,
      "created": null
    },
    {
      "id": "e36f7112-86c5-4966-b63a-6a79fe5263a7",
      "playing": 7,
      "maxPlayers": 8,
      "created": null
    },
    {
      "id": "8f7b0336-b684-4b8b-ba1c-6ffd3a1433e0",
      "playing": 7,
      "maxPlayers": 8,
      "created": null
    },
    {
      "id": "17e01df0-e5a6-459e-a1af-87a10be4ea13",
      "playing": 7,
      "maxPlayers": 8,
      "created": null
    },
    {
      "id": "33f47dcf-0830-446b-9636-b870c6a39ba2",
      "playing": 7,
      "maxPlayers": 8,
      "created": null
    },
    {
      "id": "689fe315-cc88-40ff-8e83-bf977761b5a4",
      "playing": 7,
      "maxPlayers": 8,
      "created": null
    },
    {
      "id": "872cd020-d7ea-4cb1-9a35-7d4dc8563171",
      "playing": 7,
      "maxPlayers": 8,
      "created": null
    },
    {
      "id": "314ffe67-32b1-447d-9702-22fbb5243112",
      "playing": 7,
      "maxPlayers": 8,
      "created": null
    },
    {
      "id": "42022d02-aac5-47cc-8bb4-48e65dd708f8",
      "playing": 7,
      "maxPlayers": 8,
      "created": null
    },
    {
      "id": "8ddac7bf-361f-49e3-b15d-1c45a6f6885b",
      "playing": 7,
      "maxPlayers": 8,
      "created": null
    },
    {
      "id": "459abbbc-045a-4711-b36b-bb44a3dd9e51",
      "playing": 7,
      "maxPlayers": 8,
      "created": null
    },
    {
      "id": "59ecb54b-a977-4630-9cfb-6b4bd3b9d867",
      "playing": 7,
      "maxPlayers": 8,
      "created": null
    },
    {
      "id": "d3e1b096-881a-4943-b0cf-4657323fbda7",
      "playing": 7,
      "maxPlayers": 8,
      "created": null
    },
    {
      "id": "d5105a4d-0b05-44a0-ab54-920b4458b964",
      "playing": 7,
      "maxPlayers": 8,
      "created": null
    },
    {
      "id": "ad29bbdc-a629-4358-8e67-085a8e5a08d0",
      "playing": 7,
      "maxPlayers": 8,
      "created": null
    },
    {
      "id": "ba6add45-75e1-47dd-afe0-bbbe685087ac",
      "playing": 7,
      "maxPlayers": 8,
      "created": null
    },
    {
      "id": "92490083-1074-4428-82f2-fbfda7ca22f3",
      "playing": 7,
      "maxPlayers": 8,
      "created": null
    },
    {
      "id": "bf30d015-c31c-48c3-a697-6719645f6c7c",
      "playing": 7,
      "maxPlayers": 8,
      "created": null
    },
    {
      "id": "bf924704-359f-4319-bf68-1f2e63b8cfdd",
      "playing": 7,
      "maxPlayers": 8,
      "created": null
    },
    {
      "id": "2a1cb1d8-510f-4720-b639-b6476259ebdd",
      "playing": 7,
      "maxPlayers": 8,
      "created": null
    },
    {
      "id": "f41ce414-82f8-44cc-9e3a-4f5855035326",
      "playing": 7,
      "maxPlayers": 8,
      "created": null
    },
    {
      "id": "dcdbd261-82c7-4db4-9874-7862d8c89bd7",
      "playing": 7,
      "maxPlayers": 8,
      "created": null
    },
    {
      "id": "59b54521-fc0d-42ad-8b3b-e1bde874a11e",
      "playing": 7,
      "maxPlayers": 8,
      "created": null
    },
    {
      "id": "c5dd2f73-8f82-42f3-9edb-29c281c80c7d",
      "playing": 7,
      "maxPlayers": 8,
      "created": null
    },
    {
      "id": "04c4fd59-580a-4ae5-b551-5ba6b7075085",
      "playing": 7,
      "maxPlayers": 8,
      "created": null
    },
    {
      "id": "28cc15ad-184d-4456-a15a-3495f72df3eb",
      "playing": 7,
      "maxPlayers": 8,
      "created": null
    },
    {
      "id": "e276d35b-bffd-4ec4-aaab-326529c4da63",
      "playing": 7,
      "maxPlayers": 8,
      "created": null
    },
    {
      "id": "0ce26184-4e4f-4f92-8de4-f511af015418",
      "playing": 7,
      "maxPlayers": 8,
      "created": null
    },
    {
      "id": "b36419a8-8341-404e-8265-80a00839f4df",
      "playing": 7,
      "maxPlayers": 8,
      "created": null
    },
    {
      "id": "5033874c-fb28-401f-81cc-6bd50d929495",
      "playing": 7,
      "maxPlayers": 8,
      "created": null
    },
    {
      "id": "f70c63e5-61e3-4568-8452-6f79ad0644c5",
      "playing": 7,
      "maxPlayers": 8,
      "created": null
    },
    {
      "id": "843b2f4b-2815-4d2f-9035-f388ba2d11ce",
      "playing": 7,
      "maxPlayers": 8,
      "created": null
    },
    {
      "id": "b4a562de-1565-4b84-92ab-99fe5185c529",
      "playing": 7,
      "maxPlayers": 8,
      "created": null
    },
    {
      "id": "2a5d6117-8453-4c64-b92e-1212d36179bf",
      "playing": 7,
      "maxPlayers": 8,
      "created": null
    },
    {
      "id": "189348c2-cb92-4893-986f-03df983d11c4",
      "playing": 7,
      "maxPlayers": 8,
      "created": null
    },
    {
      "id": "61292f28-7bcb-4b5f-aae5-c81f6abacd74",
      "playing": 7,
      "maxPlayers": 8,
      "created": null
    },
    {
      "id": "9d0f812d-d962-4a5c-844a-b845f1a31750",
      "playing": 7,
      "maxPlayers": 8,
      "created": null
    },
    {
      "id": "93ea159e-e59c-4d81-953e-a414e834be32",
      "playing": 7,
      "maxPlayers": 8,
      "created": null
    },
    {
      "id": "1439df9a-71b7-45b3-8bef-2ec5db62467a",
      "playing": 7,
      "maxPlayers": 8,
      "created": null
    },
    {
      "id": "1191d014-7daf-4c83-aee1-a789df6b5132",
      "playing": 7,
      "maxPlayers": 8,
      "created": null
    },
    {
      "id": "87cd100c-3392-4723-8c1f-89154e9e8517",
      "playing": 7,
      "maxPlayers": 8,
      "created": null
    },
    {
      "id": "5024a098-d7ed-4a69-b1e2-101e6e1a778b",
      "playing": 7,
      "maxPlayers": 8,
      "created": null
    },
    {
      "id": "2acc06fe-f384-4bdb-8a69-5b375ac7adf7",
      "playing": 7,
      "maxPlayers": 8,
      "created": null
    },
    {
      "id": "eb3765ed-2ee2-4f90-8bde-b8c9baba5d61",
      "playing": 7,
      "maxPlayers": 8,
      "created": null
    },
    {
      "id": "4f7eca74-cdee-4449-bd59-4cf1530f0257",
      "playing": 7,
      "maxPlayers": 8,
      "created": null
    },
    {
      "id": "2d1e9d8c-51f0-4817-811c-8679683a8995",
      "playing": 7,
      "maxPlayers": 8,
      "created": null
    },
    {
      "id": "4bfa5033-1ce0-4b0c-b129-a5746c43d6dd",
      "playing": 7,
      "maxPlayers": 8,
      "created": null
    },
    {
      "id": "d78cc0fb-d739-447b-a80f-3ef315bdd1ad",
      "playing": 7,
      "maxPlayers": 8,
      "created": null
    },
    {
      "id": "459a6d9c-6d6c-499d-a58d-89cc95537db5",
      "playing": 7,
      "maxPlayers": 8,
      "created": null
    },
    {
      "id": "5136174d-e0d8-4e65-ac84-069050542474",
      "playing": 7,
      "maxPlayers": 8,
      "created": null
    },
    {
      "id": "aad817b2-b6c4-486a-b21c-ac0893bc7477",
      "playing": 7,
      "maxPlayers": 8,
      "created": null
    },
    {
      "id": "df186ca6-83da-41ee-ae2b-a1f43ca4427a",
      "playing": 7,
      "maxPlayers": 8,
      "created": null
    },
    {
      "id": "7cb23c48-77b1-43da-a087-22a477024a71",
      "playing": 7,
      "maxPlayers": 8,
      "created": null
    },
    {
      "id": "ac8f98f0-437d-4aa6-80fc-01cd9c2f86d4",
      "playing": 7,
      "maxPlayers": 8,
      "created": null
    },
    {
      "id": "d18e0acf-baac-4d22-90cf-bd4fbbac2ae3",
      "playing": 7,
      "maxPlayers": 8,
      "created": null
    },
    {
      "id": "557a15d5-0a93-4f4d-b230-8d16f9290cc1",
      "playing": 7,
      "maxPlayers": 8,
      "created": null
    },
    {
      "id": "9b136fe7-0312-4229-aa5c-e96941faa865",
      "playing": 7,
      "maxPlayers": 8,
      "created": null
    },
    {
      "id": "624a1d11-bb98-48d0-aa05-83cdedf73f0b",
      "playing": 7,
      "maxPlayers": 8,
      "created": null
    },
    {
      "id": "546e6cef-4faa-47ac-9bb2-5306c5642d99",
      "playing": 7,
      "maxPlayers": 8,
      "created": null
    },
    {
      "id": "fc945656-74ec-45d7-8035-33a7e14961ac",
      "playing": 7,
      "maxPlayers": 8,
      "created": null
    },
    {
      "id": "ff5809d3-beee-4be6-a4ba-81c72e7cb4d2",
      "playing": 7,
      "maxPlayers": 8,
      "created": null
    },
    {
      "id": "aae686e9-9178-4721-a53d-6dd039fbfcd5",
      "playing": 7,
      "maxPlayers": 8,
      "created": null
    },
    {
      "id": "10e91358-48a7-47f2-8643-47a7060cd781",
      "playing": 7,
      "maxPlayers": 8,
      "created": null
    },
    {
      "id": "ae72ce07-b0f2-47be-a671-01279dfdcb11",
      "playing": 7,
      "maxPlayers": 8,
      "created": null
    },
    {
      "id": "bf3f1e4e-95b1-4118-9f9e-97ad09bd26a5",
      "playing": 7,
      "maxPlayers": 8,
      "created": null
    },
    {
      "id": "df7a73b4-d019-46ca-814a-8d4f6646262d",
      "playing": 7,
      "maxPlayers": 8,
      "created": null
    },
    {
      "id": "a5219664-2099-4171-b03f-9ab96a7fe36a",
      "playing": 7,
      "maxPlayers": 8,
      "created": null
    },
    {
      "id": "182eec89-efdf-450f-8046-027b99f2221c",
      "playing": 7,
      "maxPlayers": 8,
      "created": null
    },
    {
      "id": "e1e5ad4e-9752-40c6-9b8e-f20bbd15f6f5",
      "playing": 7,
      "maxPlayers": 8,
      "created": null
    },
    {
      "id": "bd56c08b-c316-422d-9d48-a80c5328740f",
      "playing": 7,
      "maxPlayers": 8,
      "created": null
    },
    {
      "id": "a97fcce1-4d9a-43bf-8507-0f45f484998e",
      "playing": 7,
      "maxPlayers": 8,
      "created": null
    },
    {
      "id": "00743e9c-1fd8-4872-a957-7bf511e2247f",
      "playing": 7,
      "maxPlayers": 8,
      "created": null
    },
    {
      "id": "48c0eebc-1682-4b37-8495-54e0d485f370",
      "playing": 7,
      "maxPlayers": 8,
      "created": null
    },
    {
      "id": "b9f674c6-1eb1-4f2f-8d09-cbc4426e2a24",
      "playing": 7,
      "maxPlayers": 8,
      "created": null
    },
    {
      "id": "c605de6b-da86-4513-91ff-bd2f6aeeddd2",
      "playing": 7,
      "maxPlayers": 8,
      "created": null
    },
    {
      "id": "191ad746-7bae-4f98-9630-a86542a74493",
      "playing": 7,
      "maxPlayers": 8,
      "created": null
    },
    {
      "id": "b0df18e4-3ae2-4ea8-9bc0-2ebfd3349e18",
      "playing": 7,
      "maxPlayers": 8,
      "created": null
    },
    {
      "id": "d9672554-be02-42ad-9f02-801adccd8422",
      "playing": 7,
      "maxPlayers": 8,
      "created": null
    },
    {
      "id": "d703b759-1e28-43b0-890c-154f115c8501",
      "playing": 7,
      "maxPlayers": 8,
      "created": null
    },
    {
      "id": "62be5960-1402-4cb2-9c5a-a195ba3e4a00",
      "playing": 7,
      "maxPlayers": 8,
      "created": null
    },
    {
      "id": "270aeeba-6a59-415b-b1c1-3272ebe7cc6a",
      "playing": 7,
      "maxPlayers": 8,
      "created": null
    },
    {
      "id": "3011261f-952b-4f9d-842d-face152a67a7",
      "playing": 7,
      "maxPlayers": 8,
      "created": null
    },
    {
      "id": "1adc2465-ebd9-4b94-a094-7554cd98b3d4",
      "playing": 7,
      "maxPlayers": 8,
      "created": null
    },
    {
      "id": "e263c610-4ae6-432b-b319-5a7ae4b0c716",
      "playing": 7,
      "maxPlayers": 8,
      "created": null
    },
    {
      "id": "7c9fa1fe-2863-4584-82fa-47e976d2798c",
      "playing": 7,
      "maxPlayers": 8,
      "created": null
    },
    {
      "id": "4eff8673-423b-49e9-bac4-b2f9bf8aab05",
      "playing": 7,
      "maxPlayers": 8,
      "created": null
    },
    {
      "id": "15b87ffe-5e1b-49ee-b0e6-82ec263c0a0a",
      "playing": 7,
      "maxPlayers": 8,
      "created": null
    },
    {
      "id": "c2d1f92c-3078-4fdc-a2ca-d648dac333f3",
      "playing": 7,
      "maxPlayers": 8,
      "created": null
    }
  ]
}